nonebot_plugin_uninfo-0.10.0.dist-info/METADATA
nonebot_plugin_uninfo-0.10.0.dist-info/WHEEL
nonebot_plugin_uninfo-0.10.0.dist-info/entry_points.txt
nonebot_plugin_uninfo-0.10.0.dist-info/licenses/LICENSE
nonebot_plugin_uninfo/__init__.py
nonebot_plugin_uninfo/adapters/__init__.py
nonebot_plugin_uninfo/adapters/bililive/__init__.py
nonebot_plugin_uninfo/adapters/bililive/main.py
nonebot_plugin_uninfo/adapters/console/__init__.py
nonebot_plugin_uninfo/adapters/console/main.py
nonebot_plugin_uninfo/adapters/discord/__init__.py
nonebot_plugin_uninfo/adapters/discord/main.py
nonebot_plugin_uninfo/adapters/dodo/__init__.py
nonebot_plugin_uninfo/adapters/dodo/main.py
nonebot_plugin_uninfo/adapters/efchat/__init__.py
nonebot_plugin_uninfo/adapters/efchat/main.py
nonebot_plugin_uninfo/adapters/feishu/__init__.py
nonebot_plugin_uninfo/adapters/feishu/main.py
nonebot_plugin_uninfo/adapters/kook/__init__.py
nonebot_plugin_uninfo/adapters/kook/main.py
nonebot_plugin_uninfo/adapters/kritor/__init__.py
nonebot_plugin_uninfo/adapters/kritor/main.py
nonebot_plugin_uninfo/adapters/mail/__init__.py
nonebot_plugin_uninfo/adapters/mail/main.py
nonebot_plugin_uninfo/adapters/milky/__init__.py
nonebot_plugin_uninfo/adapters/milky/main.py
nonebot_plugin_uninfo/adapters/minecraft/__init__.py
nonebot_plugin_uninfo/adapters/minecraft/main.py
nonebot_plugin_uninfo/adapters/mirai/__init__.py
nonebot_plugin_uninfo/adapters/mirai/main.py
nonebot_plugin_uninfo/adapters/onebot11/__init__.py
nonebot_plugin_uninfo/adapters/onebot11/main.py
nonebot_plugin_uninfo/adapters/onebot12/__init__.py
nonebot_plugin_uninfo/adapters/onebot12/main.py
nonebot_plugin_uninfo/adapters/qq/__init__.py
nonebot_plugin_uninfo/adapters/qq/main.py
nonebot_plugin_uninfo/adapters/satori/__init__.py
nonebot_plugin_uninfo/adapters/satori/main.py
nonebot_plugin_uninfo/adapters/telegram/__init__.py
nonebot_plugin_uninfo/adapters/telegram/main.py
nonebot_plugin_uninfo/adapters/wxmp/__init__.py
nonebot_plugin_uninfo/adapters/wxmp/main.py
nonebot_plugin_uninfo/config.py
nonebot_plugin_uninfo/constraint.py
nonebot_plugin_uninfo/fetch.py
nonebot_plugin_uninfo/loader.py
nonebot_plugin_uninfo/migrations/14175fde8186_init_db.py
nonebot_plugin_uninfo-0.10.0.dist-info/RECORD
