Metadata-Version: 2.1
Name: nonebot-plugin-uninfo
Version: 0.10.0
Summary: Universal Information Model for Nonebot2
Author-Email: RF-Tar-Railt <rf_tar_railt@qq.com>
License: MIT
Requires-Python: >=3.10
Requires-Dist: nonebot2>=2.4.2
Requires-Dist: importlib-metadata>=7.2.1
